gosql/__init__.py
gosql/exceptions.py
gosql/mysql.py
gosql/py.typed
gosql/core/__init__.py
gosql/core/performance.py
gosql/lib/gosql.dll
gosql/lib/gosql.h
gosql_connector-1.0.0.dist-info/licenses/LICENSE
gosql_connector-1.0.0.dist-info/METADATA
gosql_connector-1.0.0.dist-info/WHEEL
gosql_connector-1.0.0.dist-info/entry_points.txt
gosql_connector-1.0.0.dist-info/top_level.txt
gosql_connector-1.0.0.dist-info/RECORD
