Metadata-Version: 2.4
Name: gosql-connector
Version: 1.0.0
Summary: High-performance Go-based SQL connector library for Python with 2-3x better performance
Home-page: https://github.com/coffeecms/gosql
Author: CoffeeCMS Team
Author-email: CoffeeCMS Team <dev@coffeecms.com>
Maintainer-email: CoffeeCMS Team <dev@coffeecms.com>
License: MIT
Project-URL: Homepage, https://github.com/coffeecms/gosql
Project-URL: Bug Tracker, https://github.com/coffeecms/gosql/issues
Project-URL: Documentation, https://gosql.readthedocs.io
Project-URL: Source Code, https://github.com/coffeecms/gosql
Project-URL: Changelog, https://github.com/coffeecms/gosql/blob/main/CHANGELOG.md
Project-URL: Benchmarks, https://github.com/coffeecms/gosql/tree/main/benchmarks
Keywords: database,sql,mysql,postgresql,mssql,connector,performance,go,cgo,high-performance
Platform: any
Classifier: Development Status :: 4 - Beta
Classifier: Intended Audience :: Developers
Classifier: License :: OSI Approved :: MIT License
Classifier: Operating System :: OS Independent
Classifier: Programming Language :: Python :: 3
Classifier: Programming Language :: Python :: 3.7
Classifier: Programming Language :: Python :: 3.8
Classifier: Programming Language :: Python :: 3.9
Classifier: Programming Language :: Python :: 3.10
Classifier: Programming Language :: Python :: 3.11
Classifier: Programming Language :: Python :: 3.12
Classifier: Programming Language :: Go
Classifier: Topic :: Database
Classifier: Topic :: Software Development :: Libraries :: Python Modules
Provides: gosql
Requires-Python: >=3.7
License-File: LICENSE
Requires-Dist: psutil>=5.8.0
Provides-Extra: dev
Requires-Dist: pytest>=6.0; extra == "dev"
Requires-Dist: pytest-cov>=2.0; extra == "dev"
Requires-Dist: pytest-asyncio>=0.15; extra == "dev"
Requires-Dist: black>=21.0; extra == "dev"
Requires-Dist: flake8>=3.8; extra == "dev"
Requires-Dist: mypy>=0.800; extra == "dev"
Requires-Dist: isort>=5.0; extra == "dev"
Requires-Dist: pre-commit>=2.0; extra == "dev"
Provides-Extra: benchmark
Requires-Dist: mysql-connector-python>=8.0; extra == "benchmark"
Requires-Dist: psycopg2-binary>=2.8; extra == "benchmark"
Requires-Dist: pyodbc>=4.0; extra == "benchmark"
Requires-Dist: matplotlib>=3.0; extra == "benchmark"
Requires-Dist: pandas>=1.0; extra == "benchmark"
Requires-Dist: seaborn>=0.11; extra == "benchmark"
Requires-Dist: jupyter>=1.0; extra == "benchmark"
Provides-Extra: test
Requires-Dist: pytest>=6.0; extra == "test"
Requires-Dist: pytest-asyncio>=0.15; extra == "test"
Requires-Dist: pytest-xdist>=2.0; extra == "test"
Requires-Dist: docker>=5.0; extra == "test"
Requires-Dist: testcontainers>=3.0; extra == "test"
Provides-Extra: docs
Requires-Dist: sphinx>=4.0; extra == "docs"
Requires-Dist: sphinx-rtd-theme>=1.0; extra == "docs"
Requires-Dist: myst-parser>=0.15; extra == "docs"
Requires-Dist: sphinx-autodoc-typehints>=1.12; extra == "docs"
Dynamic: author
Dynamic: home-page
Dynamic: license-file
Dynamic: platform
Dynamic: provides
Dynamic: requires-python
